{
  "SimilarityTables": [
    {
      "id": 1,
      "products": ["Pera", "Manzana", "Zanahoria", "Filete", "Lenguado"],
      "similarities": [
        {
          "product1": "Pera",
          "product2": "Manzana",
          "similarity": 0.5
        },
        {
          "product1": "Pera",
          "product2": "Zanahoria",
          "similarity": 0.2
        },
        {
          "product1": "Pera",
          "product2": "Filete",
          "similarity": 0.1
        },
        {
          "product1": "Pera",
          "product2": "Lenguado",
          "similarity": 0.4
        },
        {
          "product1": "Manzana",
          "product2": "Zanahoria",
          "similarity": 0.3
        },
        {
          "product1": "Manzana",
          "product2": "Filete",
          "similarity": 0.2
        },
        {
          "product1": "Manzana",
          "product2": "Lenguado",
          "similarity": 0.5
        },
        {
          "product1": "Zanahoria",
          "product2": "Filete",
          "similarity": 0.3
        },
        {
          "product1": "Zanahoria",
          "product2": "Lenguado",
          "similarity": 0.2
        },
        {
          "product1": "Filete",
          "product2": "Lenguado",
          "similarity": 0.6
        }
      ]
    }
  ]
}
